src/ascii_converter.v

module ascii_converter (
    input [1:0] code, // 2-bit input code representing violation type
    output reg [7:0] ascii // ASCII output corresponding to code
);

    always @(*) begin
        case (code)
            2'b01: ascii = "R";  // Rule Violation
            2'b10: ascii = "P";  // Pattern Violation
            2'b11: ascii = "B";  // Both Violations
            default: ascii = 8'h00;
        endcase
    end

endmodule

src/fsm_firewall.v

module fsm_firewall (
    input clk, // Clock signal
    input rst, //reset signal
    input rule_violation, // Rule-based violation flag
    input pattern_violation, // Pattern-based violation flag


    output reg alert_out, // High when in ALERT state
    output reg firewall_block, // High when system is ISOLATED
    output reg [1:0] led_status // Current FSM state for visual status
);
    // State Encoding
    parameter NORMAL  = 2'b00;
    parameter ALERT   = 2'b01;
    parameter ISOLATE = 2'b10;
    parameter RECOVER = 2'b11;
    // Internal Registers and Wires
    reg [1:0] current_state, next_state;
    reg [1:0] alert_counter;
    reg [7:0] isolate_timer;

    wire violation = rule_violation || pattern_violation;

    // Sequential Logic – State Register & Counters
    always @(posedge clk or posedge rst) begin
        if (rst) begin
            current_state   <= NORMAL;
            alert_counter   <= 2'd0;
            isolate_timer   <= 8'd0;
        end else begin
            current_state <= next_state;

            if (violation) begin
                alert_counter <= alert_counter + 1;
            end else if (current_state == NORMAL || current_state == RECOVER) begin
                alert_counter <= 0;  
            end

            if (current_state == ISOLATE)
                isolate_timer <= isolate_timer + 1;
            else
                isolate_timer <= 0;
        end
    end

    // Combinational Logic – Next State Transition Logic
    always @(*) begin
        case (current_state)
            NORMAL: begin
                if (violation)
                    next_state = ALERT;
                else
                    next_state = NORMAL;
            end

            ALERT: begin
                if (alert_counter >= 3)
                    next_state = ISOLATE;
                else if (!violation)
                    next_state = NORMAL;
                else
                    next_state = ALERT;
            end

            ISOLATE: begin
                if (isolate_timer >= 20)
                    next_state = RECOVER;
                else
                    next_state = ISOLATE;
            end

            RECOVER: begin
                if (!violation)
                    next_state = NORMAL;
                else
                    next_state = RECOVER;
            end

            default: next_state = NORMAL;
        endcase
    end

    // Output Logic – Based on Current State
    always @(*) begin
        alert_out      = (current_state == ALERT);
        firewall_block = (current_state == ISOLATE);
        led_status     = current_state;
    end

endmodule

pattern_checker.v


module pattern_checker (
    input wire clk, //clock signal
    input wire rst, //reset
    input wire [31:0] data_in, //input data
    output reg pattern_violation, //High if any suspicious pattern is detected
    output reg repeat_flag, // High if same data repeats 3 times consecutively
    output reg signature_flag, // High if a known malicious signature is seen
    output reg [2:0] repeat_count, // Counter for repeated values (max count = 3)
    output reg [2:0] timeout_counter, // Counts the number of cycles since last repeated value
    output reg [31:0] prev_data // Stores last seen data value
);

    // Signature patterns
    parameter SIG1 = 32'hCAFEBABE;
    parameter SIG2 = 32'h0000BEEF;
    // Pattern Detection Logic
    always @(posedge clk or posedge rst) begin
        if (rst) begin
            // Reset all flags and counters
            pattern_violation <= 0;
            repeat_flag       <= 0;
            signature_flag    <= 0;
            repeat_count      <= 1;  
            timeout_counter   <= 0;
            prev_data         <= 32'h0;
        end else begin
            // Check for known signature
            signature_flag <= (data_in == SIG1 || data_in == SIG2);

            // Check for repeat pattern
            if (data_in == prev_data) begin
                if (repeat_count < 3)
                    repeat_count <= repeat_count + 1;
                repeat_flag <= (repeat_count + 1 == 3);
                timeout_counter <= 0;
            end else begin
                // Reset repeat detection
                repeat_count <= 1;  
                repeat_flag <= 0;   
                timeout_counter <= timeout_counter + 1;
            end

            // Combine both conditions
            pattern_violation <= signature_flag || repeat_flag;

            // Update previous data
            prev_data <= data_in;
        end
    end
endmodule

src/packet_filter.v


module packet_filter (
    input        clk, //clock signal
    input        rst, //reset
    input [15:0] addr_in, //input address 
    input [3:0]  cmd_in, //command input
    input [31:0] data_in, //data input
    output reg   rule_violation //High when rule is violated
);

    // Rule trigger signals
    wire r1_violation, r2_violation, r3_violation;
    // Rule Definitions
    assign r1_violation = (addr_in == 16'h0000);
    assign r2_violation = (data_in == 32'hDEADBEEF);
    assign r3_violation = ((cmd_in == 4'b0010) && (addr_in == 16'h1234)); 
    // Rule Violation Output Logic
    always @(posedge clk or posedge rst) begin
        if (rst)
            rule_violation <= 0;
        else
            rule_violation <= r1_violation | r2_violation | r3_violation;
    end

endmodule

top_firewall.v


module top_firewall (
    input clk, // clock signal
    input rst, // reset signal
    input [31:0] data_in, // data input
    input [15:0] addr, // address input
    input wr_en, // write enable
    input rd_en, // read enable

    output alert_out, // High if system is in ALERT state
    output firewall_block, // High if system is in ISOLATES state
    output [1:0] led_status // FSM current state for visual status
);
    // Internal Wires
    wire rule_violation;
    wire pattern_violation;
    wire [1:0] violation_code;
   
    assign violation_code = {pattern_violation, rule_violation};

    // Packet Filter Module – Rule-Based Violation Detection
    packet_filter u1 (
        .clk(clk),
        .rst(rst),
        .addr_in(addr),
        .cmd_in({2'b00, wr_en, rd_en}),
        .data_in(data_in),
        .rule_violation(rule_violation)
    );

// Pattern Checker Module – Signature and Repeat Detection
wire repeat_flag;
wire signature_flag;
wire [2:0] repeat_count;
wire [2:0] timeout_counter;
wire [31:0] prev_data;

pattern_checker u2 (
    .clk(clk),
    .rst(rst),
    .repeat_count(repeat_count),        
    .timeout_counter(timeout_counter),
    .prev_data(prev_data),         
    .data_in(data_in),
    .repeat_flag(repeat_flag),
    .signature_flag(signature_flag),
    .pattern_violation(pattern_violation)
);

    // FSM Firewall Controller – Handles State Transitions
    fsm_firewall u3 (
        .clk(clk),
        .rst(rst),
        .rule_violation(rule_violation),
        .pattern_violation(pattern_violation),
        .alert_out(alert_out),
        .firewall_block(firewall_block),
        .led_status(led_status)
    );
    wire [7:0] ascii_msg;
   
    // ASCII Converter – Converts Violation Code to Message
    ascii_converter u4 (
        .code(violation_code),
        .ascii(ascii_msg)
    );

endmodule

tb_top_firewall.v
`timescale 1ns / 1ps

module tb_top_firewall;
    // Inputs
    reg clk, rst;
    reg [31:0] data_in;
    reg [15:0] addr;
    reg wr_en, rd_en;
    // Outputs
    wire alert_out, firewall_block;
    wire [1:0] led_status;
    

    // DUT instantiation
    top_firewall uut (
        .clk(clk),
        .rst(rst),
        .data_in(data_in),
        .addr(addr),
        .wr_en(wr_en),
        .rd_en(rd_en),
        .alert_out(alert_out),
        .firewall_block(firewall_block),
        .led_status(led_status)
    );

    // Clock Generation – 50MHz (20ns period)
    initial clk = 0;
    always #10 clk = ~clk;
    // Simulation Sequence
    initial begin
        // Dump VCD for waveform view
        $dumpfile("top_firewall.vcd");
        $dumpvars(0, tb_top_firewall);
        $dumpvars(0, tb_top_firewall.uut.u1.rule_violation);
        $dumpvars(0, tb_top_firewall.uut.u2.pattern_violation);
        $dumpvars(0, tb_top_firewall.uut.u2.repeat_flag);
        $dumpvars(0, tb_top_firewall.uut.u2.signature_flag);

        // Initial Reset
        rst = 1; data_in = 0; addr = 0; wr_en = 0; rd_en = 0;
        #20;
        rst = 0;

        // Test 1: Clean Packet
        addr = 16'h1000; data_in = 32'h12345678; wr_en = 0; rd_en = 1;
        #20;

        // Test 2: Rule Violation (write to 0x1234)
        addr = 16'h1234; data_in = 32'hDEADBEEF; wr_en = 1; rd_en = 0;
        #20;

        // Test 3: Signature Pattern Match (CAFEBABE)
        addr = 16'h2000; data_in = 32'hCAFEBABE; wr_en = 0; rd_en = 1;
        #20;

        // Test 4: Another Signature Pattern (0000BEEF)
        addr = 16'h2000; data_in = 32'h0000BEEF; wr_en = 0; rd_en = 1;
        #20;
        
         addr = 16'h3000; data_in = 32'h11111111; wr_en = 0; rd_en = 1;
        #20;
         addr = 16'h3000; data_in = 32'h11111111; wr_en = 0; rd_en = 1;
        #20;

        // Test 5: Repeat Violation (3x same data)
        addr = 16'h2000; data_in = 32'hAAAA5555; wr_en = 0; rd_en = 1;
        #20;
        addr = 16'h2000; data_in = 32'hAAAA5555; wr_en = 0; rd_en = 1;
        #20;
        addr = 16'h2000; data_in = 32'hAAAA5555; wr_en = 0; rd_en = 1;
        #20;
        

        // Test 7: Both Violations (DEADBEEF + forbidden addr)
        addr = 16'h0000; data_in = 32'hDEADBEEF; wr_en = 1; rd_en = 0;
        #20;
         addr = 16'h0000; data_in = 32'hDEADBEEF; wr_en = 1; rd_en = 0;
        #20;
         addr = 16'h1234; data_in = 32'hDEADBEEF; wr_en = 1; rd_en = 0;
        #20;
        #400

        addr = 16'h2000; data_in = 32'hAAAA5555; wr_en = 0; rd_en = 1;
        #20;
        addr = 16'h2000; data_in = 32'hAAAA5555; wr_en = 0; rd_en = 1;
        #20;
        addr = 16'h2000; data_in = 32'hAAAA5555; wr_en = 0; rd_en = 1;
        #20;
        #400;
         addr = 16'h3000; data_in = 32'h11111111; wr_en = 0; rd_en = 1;
        #20;
        


        $finish;
    end

endmodule

Vivado/project_3.sim/sim_1/behav/xsim/top_firewall.vcd
$date
   Tue Jul 29 18:57:17 2025
$end

$version
  2024.2.0
  $dumpfile ("top_firewall.vcd") 
$end

$timescale
  1ps
$end

$scope module tb_top_firewall $end
$var reg 1 ! clk $end
$var reg 1 " rst $end
$var reg 32 # data_in [31:0] $end
$var reg 16 $ addr [15:0] $end
$var reg 1 % wr_en $end
$var reg 1 & rd_en $end
$var wire 1 ' alert_out $end
$var wire 1 ( firewall_block $end
$var wire 2 ) led_status [1:0] $end
$scope module uut $end
$var wire 1 * clk $end
$var wire 1 + rst $end
$var wire 32 , data_in [31:0] $end
$var wire 16 - addr [15:0] $end
$var wire 1 . wr_en $end
$var wire 1 / rd_en $end
$var wire 1 ' alert_out $end
$var wire 1 ( firewall_block $end
$var wire 2 ) led_status [1:0] $end
$var wire 1 0 rule_violation $end
$var wire 1 1 pattern_violation $end
$var wire 2 2 violation_code [1:0] $end
$var wire 1 3 repeat_flag $end
$var wire 1 4 signature_flag $end
$var wire 3 5 repeat_count [2:0] $end
$var wire 3 6 timeout_counter [2:0] $end
$var wire 32 7 prev_data [31:0] $end
$var wire 8 8 ascii_msg [7:0] $end
$scope module u1 $end
$var wire 1 * clk $end
$var wire 1 + rst $end
$var wire 16 - addr_in [15:0] $end
$var wire 4 9 cmd_in [3:0] $end
$var wire 32 , data_in [31:0] $end
$var reg 1 : rule_violation $end
$var wire 1 ; r1_violation $end
$var wire 1 < r2_violation $end
$var wire 1 = r3_violation $end
$upscope $end
$scope module u2 $end
$var wire 1 * clk $end
$var wire 1 + rst $end
$var wire 32 , data_in [31:0] $end
$var reg 1 > pattern_violation $end
$var reg 1 ? repeat_flag $end
$var reg 1 @ signature_flag $end
$var reg 3 A repeat_count [2:0] $end
$var reg 3 B timeout_counter [2:0] $end
$var reg 32 C prev_data [31:0] $end
$upscope $end
$scope module u3 $end
$var wire 1 * clk $end
$var wire 1 + rst $end
$var wire 1 0 rule_violation $end
$var wire 1 1 pattern_violation $end
$var reg 1 D alert_out $end
$var reg 1 E firewall_block $end
$var reg 2 F led_status [1:0] $end
$var reg 2 G current_state [1:0] $end
$var reg 2 H next_state [1:0] $end
$var reg 2 I alert_counter [1:0] $end
$var reg 8 J isolate_timer [7:0] $end
$var wire 1 K violation $end
$upscope $end
$scope module u4 $end
$var wire 2 2 code [1:0] $end
$var reg 8 L ascii [7:0] $end
$upscope $end
$upscope $end
$upscope $end
$enddefinitions $end

#0
$dumpvars
0!
1"
b0 #
b0 $
0%
0&
0'
0(
b0 )
0*
1+
b0 ,
b0 -
0.
0/
00
01
b0 2
03
04
b1 5
b0 6
b0 7
b0 8
b0 9
0:
1;
0<
0=
0>
0?
0@
b1 A
b0 B
b0 C
0D
0E
b0 F
b0 G
b0 H
b0 I
b0 J
0K
b0 L
$end

#10000
1!
1*

#20000
0!
0"
b10010001101000101011001111000 #
b1000000000000 $
1&
0*
0+
b10010001101000101011001111000 ,
b1000000000000 -
1/
b1 9
0;

#30000
1!
1*
b1 6
b10010001101000101011001111000 7
b1 B
b10010001101000101011001111000 C

#40000
0!
b11011110101011011011111011101111 #
b1001000110100 $
1%
0&
0*
b11011110101011011011111011101111 ,
b1001000110100 -
1.
0/
b10 9
1<
1=

#50000
1!
1*
10
b1 2
b10 6
b11011110101011011011111011101111 7
b1010010 8
1:
b10 B
b11011110101011011011111011101111 C
b1 H
1K
b1010010 L

#60000
0!
b11001010111111101011101010111110 #
b10000000000000 $
0%
1&
0*
b11001010111111101011101010111110 ,
b10000000000000 -
0.
1/
b1 9
0<
0=

#70000
1!
1'
b1 )
1*
00
b0 2
14
b11 6
b11001010111111101011101010111110 7
b0 8
0:
1@
b11 B
b11001010111111101011101010111110 C
1D
b1 F
b1 G
b0 H
b1 I
0K
b0 L

#80000
0!
b1011111011101111 #
0*
b1011111011101111 ,

#90000
1!
0'
b0 )
1*
11
b10 2
b100 6
b1011111011101111 7
b1010000 8
1>
b100 B
b1011111011101111 C
0D
b0 F
b0 G
b1 H
1K
b1010000 L

#100000
0!
b10001000100010001000100010001 #
b11000000000000 $
0*
b10001000100010001000100010001 ,
b11000000000000 -

#110000
1!
1'
b1 )
1*
04
b101 6
b10001000100010001000100010001 7
0@
b101 B
b10001000100010001000100010001 C
1D
b1 F
b1 G
b10 I

#120000
0!
0*

#130000
1!
1*
01
b0 2
b10 5
b0 6
b0 8
0>
b10 A
b0 B
b10 H
b11 I
0K
b0 L

#140000
0!
b10101010101010100101010101010101 #
b10000000000000 $
0*
b10101010101010100101010101010101 ,
b10000000000000 -

#150000
1!
0'
1(
b10 )
1*
b1 5
b1 6
b10101010101010100101010101010101 7
b1 A
b1 B
b10101010101010100101010101010101 C
0D
1E
b10 F
b10 G

#160000
0!
0*

#170000
1!
1*
b10 5
b0 6
b10 A
b0 B
b1 J

#180000
0!
0*

#190000
1!
1*
13
b11 5
1?
b11 A
b10 J

#200000
0!
b11011110101011011011111011101111 #
b0 $
1%
0&
0*
b11011110101011011011111011101111 ,
b0 -
1.
0/
b10 9
1;
1<

#210000
1!
1*
10
11
b11 2
03
b1 5
b1 6
b11011110101011011011111011101111 7
b1000010 8
1:
1>
0?
b1 A
b1 B
b11011110101011011011111011101111 C
b11 J
1K
b1000010 L

#220000
0!
0*

#230000
1!
1*
01
b1 2
b10 5
b0 6
b1010010 8
0>
b10 A
b0 B
b0 I
b100 J
b1010010 L

#240000
0!
b1001000110100 $
0*
b1001000110100 -
0;
1=

#250000
1!
1*
13
b11 5
1?
b11 A
b1 I
b101 J

#260000
0!
0*

#270000
1!
1*
11
b11 2
03
b1000010 8
1>
0?
b10 I
b110 J
b1000010 L

#280000
0!
0*

#290000
1!
1*
01
b1 2
b1010010 8
0>
b11 I
b111 J
b1010010 L

#300000
0!
0*

#310000
1!
1*
b0 I
b1000 J

#320000
0!
0*

#330000
1!
1*
b1 I
b1001 J

#340000
0!
0*

#350000
1!
1*
b10 I
b1010 J

#360000
0!
0*

#370000
1!
1*
b11 I
b1011 J

#380000
0!
0*

#390000
1!
1*
b0 I
b1100 J

#400000
0!
0*

#410000
1!
1*
b1 I
b1101 J

#420000
0!
0*

#430000
1!
1*
b10 I
b1110 J

#440000
0!
0*

#450000
1!
1*
b11 I
b1111 J

#460000
0!
0*

#470000
1!
1*
b0 I
b10000 J

#480000
0!
0*

#490000
1!
1*
b1 I
b10001 J

#500000
0!
0*

#510000
1!
1*
b10 I
b10010 J

#520000
0!
0*

#530000
1!
1*
b11 I
b10011 J

#540000
0!
0*

#550000
1!
1*
b11 H
b0 I
b10100 J

#560000
0!
0*

#570000
1!
0(
b11 )
1*
0E
b11 F
b11 G
b1 I
b10101 J

#580000
0!
0*

#590000
1!
1*
b10 I
b0 J

#600000
0!
0*

#610000
1!
1*
b11 I

#620000
0!
0*

#630000
1!
1*
b0 I

#640000
0!
0*

#650000
1!
1*
b1 I

#660000
0!
b10101010101010100101010101010101 #
b10000000000000 $
0%
1&
0*
b10101010101010100101010101010101 ,
b10000000000000 -
0.
1/
b1 9
0<
0=

#670000
1!
1*
00
b0 2
b1 5
b1 6
b10101010101010100101010101010101 7
b0 8
0:
b1 A
b1 B
b10101010101010100101010101010101 C
b0 H
b10 I
0K
b0 L

#680000
0!
0*

#690000
1!
b0 )
1*
b10 5
b0 6
b10 A
b0 B
b0 F
b0 G
b0 I

#700000
0!
0*

#710000
1!
1*
13
b11 5
1?
b11 A

#720000
0!
0*

#730000
1!
1*
11
b10 2
03
b1010000 8
1>
0?
b1 H
1K
b1010000 L

#740000
0!
0*

#750000
1!
1'
b1 )
1*
01
b0 2
b0 8
0>
1D
b1 F
b1 G
b0 H
b1 I
0K
b0 L

#760000
0!
0*

#770000
1!
0'
b0 )
1*
0D
b0 F
b0 G

#780000
0!
0*

#790000
1!
1*
b0 I

