src/ascii_converter.v

module ascii_converter (
    input [1:0] code, // 2-bit input code representing violation type
    output reg [7:0] ascii // ASCII output corresponding to code
);

    always @(*) begin
        case (code)
            2'b01: ascii = "R";  // Rule Violation
            2'b10: ascii = "P";  // Pattern Violation
            2'b11: ascii = "B";  // Both Violations
            default: ascii = 8'h00;
        endcase
    end

endmodule

src/fsm_firewall.v

module fsm_firewall (
    input clk, // Clock signal
    input rst, //reset signal
    input rule_violation, // Rule-based violation flag
    input pattern_violation, // Pattern-based violation flag


    output reg alert_out, // High when in ALERT state
    output reg firewall_block, // High when system is ISOLATED
    output reg [1:0] led_status // Current FSM state for visual status
);
    // State Encoding
    parameter NORMAL  = 2'b00;
    parameter ALERT   = 2'b01;
    parameter ISOLATE = 2'b10;
    parameter RECOVER = 2'b11;
    // Internal Registers and Wires
    reg [1:0] current_state, next_state;
    reg [1:0] alert_counter;
    reg [7:0] isolate_timer;

    wire violation = rule_violation || pattern_violation;

    // Sequential Logic – State Register & Counters
    always @(posedge clk or posedge rst) begin
        if (rst) begin
            current_state   <= NORMAL;
            alert_counter   <= 2'd0;
            isolate_timer   <= 8'd0;
        end else begin
            current_state <= next_state;

            if (violation) begin
                alert_counter <= alert_counter + 1;
            end else if (current_state == NORMAL || current_state == RECOVER) begin
                alert_counter <= 0;  
            end

            if (current_state == ISOLATE)
                isolate_timer <= isolate_timer + 1;
            else
                isolate_timer <= 0;
        end
    end

    // Combinational Logic – Next State Transition Logic
    always @(*) begin
        case (current_state)
            NORMAL: begin
                if (violation)
                    next_state = ALERT;
                else
                    next_state = NORMAL;
            end

            ALERT: begin
                if (alert_counter >= 3)
                    next_state = ISOLATE;
                else if (!violation)
                    next_state = NORMAL;
                else
                    next_state = ALERT;
            end

            ISOLATE: begin
                if (isolate_timer >= 20)
                    next_state = RECOVER;
                else
                    next_state = ISOLATE;
            end

            RECOVER: begin
                if (!violation)
                    next_state = NORMAL;
                else
                    next_state = RECOVER;
            end

            default: next_state = NORMAL;
        endcase
    end

    // Output Logic – Based on Current State
    always @(*) begin
        alert_out      = (current_state == ALERT);
        firewall_block = (current_state == ISOLATE);
        led_status     = current_state;
    end

endmodule

pattern_checker.v


module pattern_checker (
    input wire clk, //clock signal
    input wire rst, //reset
    input wire [31:0] data_in, //input data
    output reg pattern_violation, //High if any suspicious pattern is detected
    output reg repeat_flag, // High if same data repeats 3 times consecutively
    output reg signature_flag, // High if a known malicious signature is seen
    output reg [2:0] repeat_count, // Counter for repeated values (max count = 3)
    output reg [2:0] timeout_counter, // Counts the number of cycles since last repeated value
    output reg [31:0] prev_data // Stores last seen data value
);

    // Signature patterns
    parameter SIG1 = 32'hCAFEBABE;
    parameter SIG2 = 32'h0000BEEF;
    // Pattern Detection Logic
    always @(posedge clk or posedge rst) begin
        if (rst) begin
            // Reset all flags and counters
            pattern_violation <= 0;
            repeat_flag       <= 0;
            signature_flag    <= 0;
            repeat_count      <= 1;  
            timeout_counter   <= 0;
            prev_data         <= 32'h0;
        end else begin
            // Check for known signature
            signature_flag <= (data_in == SIG1 || data_in == SIG2);

            // Check for repeat pattern
            if (data_in == prev_data) begin
                if (repeat_count < 3)
                    repeat_count <= repeat_count + 1;
                repeat_flag <= (repeat_count + 1 == 3);
                timeout_counter <= 0;
            end else begin
                // Reset repeat detection
                repeat_count <= 1;  
                repeat_flag <= 0;   
                timeout_counter <= timeout_counter + 1;
            end

            // Combine both conditions
            pattern_violation <= signature_flag || repeat_flag;

            // Update previous data
            prev_data <= data_in;
        end
    end
endmodule

src/packet_filter.v


module packet_filter (
    input        clk, //clock signal
    input        rst, //reset
    input [15:0] addr_in, //input address 
    input [3:0]  cmd_in, //command input
    input [31:0] data_in, //data input
    output reg   rule_violation //High when rule is violated
);

    // Rule trigger signals
    wire r1_violation, r2_violation, r3_violation;
    // Rule Definitions
    assign r1_violation = (addr_in == 16'h0000);
    assign r2_violation = (data_in == 32'hDEADBEEF);
    assign r3_violation = ((cmd_in == 4'b0010) && (addr_in == 16'h1234)); 
    // Rule Violation Output Logic
    always @(posedge clk or posedge rst) begin
        if (rst)
            rule_violation <= 0;
        else
            rule_violation <= r1_violation | r2_violation | r3_violation;
    end

endmodule

top_firewall.v


module top_firewall (
    input clk, // clock signal
    input rst, // reset signal
    input [31:0] data_in, // data input
    input [15:0] addr, // address input
    input wr_en, // write enable
    input rd_en, // read enable

    output alert_out, // High if system is in ALERT state
    output firewall_block, // High if system is in ISOLATES state
    output [1:0] led_status // FSM current state for visual status
);
    // Internal Wires
    wire rule_violation;
    wire pattern_violation;
    wire [1:0] violation_code;
   
    assign violation_code = {pattern_violation, rule_violation};

    // Packet Filter Module – Rule-Based Violation Detection
    packet_filter u1 (
        .clk(clk),
        .rst(rst),
        .addr_in(addr),
        .cmd_in({2'b00, wr_en, rd_en}),
        .data_in(data_in),
        .rule_violation(rule_violation)
    );

// Pattern Checker Module – Signature and Repeat Detection
wire repeat_flag;
wire signature_flag;
wire [2:0] repeat_count;
wire [2:0] timeout_counter;
wire [31:0] prev_data;

pattern_checker u2 (
    .clk(clk),
    .rst(rst),
    .repeat_count(repeat_count),        
    .timeout_counter(timeout_counter),
    .prev_data(prev_data),         
    .data_in(data_in),
    .repeat_flag(repeat_flag),
    .signature_flag(signature_flag),
    .pattern_violation(pattern_violation)
);

    // FSM Firewall Controller – Handles State Transitions
    fsm_firewall u3 (
        .clk(clk),
        .rst(rst),
        .rule_violation(rule_violation),
        .pattern_violation(pattern_violation),
        .alert_out(alert_out),
        .firewall_block(firewall_block),
        .led_status(led_status)
    );
    wire [7:0] ascii_msg;
   
    // ASCII Converter – Converts Violation Code to Message
    ascii_converter u4 (
        .code(violation_code),
        .ascii(ascii_msg)
    );

endmodule

tb_top_firewall.v
`timescale 1ns / 1ps

module tb_top_firewall;
    // Inputs
    reg clk, rst;
    reg [31:0] data_in;
    reg [15:0] addr;
    reg wr_en, rd_en;
    // Outputs
    wire alert_out, firewall_block;
    wire [1:0] led_status;
    

    // DUT instantiation
    top_firewall uut (
        .clk(clk),
        .rst(rst),
        .data_in(data_in),
        .addr(addr),
        .wr_en(wr_en),
        .rd_en(rd_en),
        .alert_out(alert_out),
        .firewall_block(firewall_block),
        .led_status(led_status)
    );

    // Clock Generation – 50MHz (20ns period)
    initial clk = 0;
    always #10 clk = ~clk;
    // Simulation Sequence
    initial begin
        // Dump VCD for waveform view
        $dumpfile("top_firewall.vcd");
        $dumpvars(0, tb_top_firewall);
        $dumpvars(0, tb_top_firewall.uut.u1.rule_violation);
        $dumpvars(0, tb_top_firewall.uut.u2.pattern_violation);
        $dumpvars(0, tb_top_firewall.uut.u2.repeat_flag);
        $dumpvars(0, tb_top_firewall.uut.u2.signature_flag);

        // Initial Reset
        rst = 1; data_in = 0; addr = 0; wr_en = 0; rd_en = 0;
        #20;
        rst = 0;

        // Test 1: Clean Packet
        addr = 16'h1000; data_in = 32'h12345678; wr_en = 0; rd_en = 1;
        #20;

        // Test 2: Rule Violation (write to 0x1234)
        addr = 16'h1234; data_in = 32'hDEADBEEF; wr_en = 1; rd_en = 0;
        #20;

        // Test 3: Signature Pattern Match (CAFEBABE)
        addr = 16'h2000; data_in = 32'hCAFEBABE; wr_en = 0; rd_en = 1;
        #20;

        // Test 4: Another Signature Pattern (0000BEEF)
        addr = 16'h2000; data_in = 32'h0000BEEF; wr_en = 0; rd_en = 1;
        #20;
        
         addr = 16'h3000; data_in = 32'h11111111; wr_en = 0; rd_en = 1;
        #20;
         addr = 16'h3000; data_in = 32'h11111111; wr_en = 0; rd_en = 1;
        #20;

        // Test 5: Repeat Violation (3x same data)
        addr = 16'h2000; data_in = 32'hAAAA5555; wr_en = 0; rd_en = 1;
        #20;
        addr = 16'h2000; data_in = 32'hAAAA5555; wr_en = 0; rd_en = 1;
        #20;
        addr = 16'h2000; data_in = 32'hAAAA5555; wr_en = 0; rd_en = 1;
        #20;
        

        // Test 7: Both Violations (DEADBEEF + forbidden addr)
        addr = 16'h0000; data_in = 32'hDEADBEEF; wr_en = 1; rd_en = 0;
        #20;
         addr = 16'h0000; data_in = 32'hDEADBEEF; wr_en = 1; rd_en = 0;
        #20;
         addr = 16'h1234; data_in = 32'hDEADBEEF; wr_en = 1; rd_en = 0;
        #20;
        #400

        addr = 16'h2000; data_in = 32'hAAAA5555; wr_en = 0; rd_en = 1;
        #20;
        addr = 16'h2000; data_in = 32'hAAAA5555; wr_en = 0; rd_en = 1;
        #20;
        addr = 16'h2000; data_in = 32'hAAAA5555; wr_en = 0; rd_en = 1;
        #20;
        #400;
         addr = 16'h3000; data_in = 32'h11111111; wr_en = 0; rd_en = 1;
        #20;
        


        $finish;
    end

endmodule

top_firewall.vcd
$date
	Tue Jul 29 19:36:05 2025
$end
$version
	Icarus Verilog
$end
$timescale
	1ps
$end
$scope module tb_top_firewall $end
$var wire 2 ! led_status [1:0] $end
$var wire 1 " firewall_block $end
$var wire 1 # alert_out $end
$var reg 16 $ addr [15:0] $end
$var reg 1 % clk $end
$var reg 32 & data_in [31:0] $end
$var reg 1 ' rd_en $end
$var reg 1 ( rst $end
$var reg 1 ) wr_en $end
$scope module uut $end
$var wire 16 * addr [15:0] $end
$var wire 1 % clk $end
$var wire 32 + data_in [31:0] $end
$var wire 1 ' rd_en $end
$var wire 1 ( rst $end
$var wire 1 ) wr_en $end
$var wire 2 , violation_code [1:0] $end
$var wire 3 - timeout_counter [2:0] $end
$var wire 1 . signature_flag $end
$var wire 1 / rule_violation $end
$var wire 1 0 repeat_flag $end
$var wire 3 1 repeat_count [2:0] $end
$var wire 32 2 prev_data [31:0] $end
$var wire 1 3 pattern_violation $end
$var wire 2 4 led_status [1:0] $end
$var wire 1 " firewall_block $end
$var wire 8 5 ascii_msg [7:0] $end
$var wire 1 # alert_out $end
$scope module u1 $end
$var wire 16 6 addr_in [15:0] $end
$var wire 1 % clk $end
$var wire 4 7 cmd_in [3:0] $end
$var wire 32 8 data_in [31:0] $end
$var wire 1 9 r3_violation $end
$var wire 1 ( rst $end
$var wire 1 : r2_violation $end
$var wire 1 ; r1_violation $end
$var reg 1 / rule_violation $end
$upscope $end
$scope module u2 $end
$var wire 1 % clk $end
$var wire 32 < data_in [31:0] $end
$var wire 1 ( rst $end
$var reg 1 3 pattern_violation $end
$var reg 32 = prev_data [31:0] $end
$var reg 3 > repeat_count [2:0] $end
$var reg 1 0 repeat_flag $end
$var reg 1 . signature_flag $end
$var reg 3 ? timeout_counter [2:0] $end
$upscope $end
$scope module u3 $end
$var wire 1 % clk $end
$var wire 1 3 pattern_violation $end
$var wire 1 ( rst $end
$var wire 1 / rule_violation $end
$var wire 1 @ violation $end
$var reg 2 A alert_counter [1:0] $end
$var reg 1 # alert_out $end
$var reg 2 B current_state [1:0] $end
$var reg 1 " firewall_block $end
$var reg 8 C isolate_timer [7:0] $end
$var reg 2 D led_status [1:0] $end
$var reg 2 E next_state [1:0] $end
$upscope $end
$scope module u4 $end
$var wire 2 F code [1:0] $end
$var reg 8 G ascii [7:0] $end
$upscope $end
$upscope $end
$upscope $end
$enddefinitions $end
#0
$dumpvars
b0 G
b0 F
b0 E
b0 D
b0 C
b0 B
b0 A
0@
b0 ?
b1 >
b0 =
b0 <
1;
0:
09
b0 8
b0 7
b0 6
b0 5
b0 4
03
b0 2
b1 1
00
0/
0.
b0 -
b0 ,
b0 +
b0 *
0)
1(
0'
b0 &
0%
b0 $
0#
0"
b0 !
$end
#10000
1%
#20000
0%
b1 7
1'
b10010001101000101011001111000 &
b10010001101000101011001111000 +
b10010001101000101011001111000 8
b10010001101000101011001111000 <
0;
b1000000000000 $
b1000000000000 *
b1000000000000 6
0(
#30000
b10010001101000101011001111000 2
b10010001101000101011001111000 =
b1 -
b1 ?
1%
#40000
19
0%
0'
b10 7
1)
1:
b11011110101011011011111011101111 &
b11011110101011011011111011101111 +
b11011110101011011011111011101111 8
b11011110101011011011111011101111 <
b1001000110100 $
b1001000110100 *
b1001000110100 6
#50000
b1 E
1@
b1010010 5
b1010010 G
b11011110101011011011111011101111 2
b11011110101011011011111011101111 =
b10 -
b10 ?
b1 ,
b1 F
1/
1%
#60000
09
0%
1'
b1 7
0)
0:
b11001010111111101011101010111110 &
b11001010111111101011101010111110 +
b11001010111111101011101010111110 8
b11001010111111101011101010111110 <
b10000000000000 $
b10000000000000 *
b10000000000000 6
#70000
b0 E
0@
b0 5
b0 G
b1 !
b1 4
b1 D
1#
b0 ,
b0 F
0/
b11001010111111101011101010111110 2
b11001010111111101011101010111110 =
b11 -
b11 ?
1.
b1 A
b1 B
1%
#80000
0%
b1011111011101111 &
b1011111011101111 +
b1011111011101111 8
b1011111011101111 <
#90000
b0 !
b0 4
b0 D
0#
b1 E
1@
b1010000 5
b1010000 G
b0 B
b1011111011101111 2
b1011111011101111 =
b10 ,
b10 F
13
b100 -
b100 ?
1%
#100000
0%
b10001000100010001000100010001 &
b10001000100010001000100010001 +
b10001000100010001000100010001 8
b10001000100010001000100010001 <
b11000000000000 $
b11000000000000 *
b11000000000000 6
#110000
b1 !
b1 4
b1 D
1#
b10001000100010001000100010001 2
b10001000100010001000100010001 =
b101 -
b101 ?
0.
b10 A
b1 B
1%
#120000
0%
#130000
b10 E
0@
b0 5
b0 G
b11 A
b0 ,
b0 F
03
b0 -
b0 ?
b10 1
b10 >
1%
#140000
0%
b10101010101010100101010101010101 &
b10101010101010100101010101010101 +
b10101010101010100101010101010101 8
b10101010101010100101010101010101 <
b10000000000000 $
b10000000000000 *
b10000000000000 6
#150000
b10 !
b10 4
b10 D
1"
0#
b10101010101010100101010101010101 2
b10101010101010100101010101010101 =
b1 -
b1 ?
b1 1
b1 >
b10 B
1%
#160000
0%
#170000
b1 C
b0 -
b0 ?
b10 1
b10 >
1%
#180000
0%
#190000
10
b11 1
b11 >
b10 C
1%
#200000
0%
0'
b10 7
1)
1:
b11011110101011011011111011101111 &
b11011110101011011011111011101111 +
b11011110101011011011111011101111 8
b11011110101011011011111011101111 <
1;
b0 $
b0 *
b0 6
#210000
1@
b1000010 5
b1000010 G
b11 C
b11011110101011011011111011101111 2
b11011110101011011011111011101111 =
13
b1 -
b1 ?
00
b1 1
b1 >
b11 ,
b11 F
1/
1%
#220000
0%
#230000
b1010010 5
b1010010 G
b1 ,
b1 F
03
b0 -
b0 ?
b10 1
b10 >
b100 C
b0 A
1%
#240000
19
0%
0;
b1001000110100 $
b1001000110100 *
b1001000110100 6
#250000
b101 C
b1 A
10
b11 1
b11 >
1%
#260000
0%
#270000
b1000010 5
b1000010 G
b11 ,
b11 F
13
00
b110 C
b10 A
1%
#280000
0%
#290000
b1010010 5
b1010010 G
b111 C
b11 A
b1 ,
b1 F
03
1%
#300000
0%
#310000
b1000 C
b0 A
1%
#320000
0%
#330000
b1001 C
b1 A
1%
#340000
0%
#350000
b1010 C
b10 A
1%
#360000
0%
#370000
b1011 C
b11 A
1%
#380000
0%
#390000
b1100 C
b0 A
1%
#400000
0%
#410000
b1101 C
b1 A
1%
#420000
0%
#430000
b1110 C
b10 A
1%
#440000
0%
#450000
b1111 C
b11 A
1%
#460000
0%
#470000
b10000 C
b0 A
1%
#480000
0%
#490000
b10001 C
b1 A
1%
#500000
0%
#510000
b10010 C
b10 A
1%
#520000
0%
#530000
b10011 C
b11 A
1%
#540000
0%
#550000
b11 E
b10100 C
b0 A
1%
#560000
0%
#570000
b11 !
b11 4
b11 D
0"
b10101 C
b1 A
b11 B
1%
#580000
0%
#590000
b0 C
b10 A
1%
#600000
0%
#610000
b11 A
1%
#620000
0%
#630000
b0 A
1%
#640000
0%
#650000
b1 A
1%
#660000
09
0%
1'
b1 7
0)
0:
b10101010101010100101010101010101 &
b10101010101010100101010101010101 +
b10101010101010100101010101010101 8
b10101010101010100101010101010101 <
b10000000000000 $
b10000000000000 *
b10000000000000 6
#670000
b0 E
0@
b0 5
b0 G
b0 ,
b0 F
0/
b10101010101010100101010101010101 2
b10101010101010100101010101010101 =
b1 -
b1 ?
b1 1
b1 >
b10 A
1%
#680000
0%
#690000
b0 !
b0 4
b0 D
b0 A
b0 B
b0 -
b0 ?
b10 1
b10 >
1%
#700000
0%
#710000
10
b11 1
b11 >
1%
#720000
0%
#730000
b1 E
1@
b1010000 5
b1010000 G
b10 ,
b10 F
13
00
1%
#740000
0%
#750000
b0 E
0@
b0 5
b0 G
b1 !
b1 4
b1 D
1#
b0 ,
b0 F
03
b1 A
b1 B
1%
#760000
0%
#770000
b0 !
b0 4
b0 D
0#
b0 B
1%
#780000
0%
#790000
b0 A
1%
#800000
0%
#810000
1%
#820000
0%
#830000
1%
#840000
0%
#850000
1%
#860000
0%
#870000
1%
#880000
0%
#890000
1%
#900000
0%
#910000
1%
#920000
0%
#930000
1%
#940000
0%
#950000
1%
#960000
0%
#970000
1%
#980000
0%
#990000
1%
#1000000
0%
#1010000
1%
#1020000
0%
#1030000
1%
#1040000
0%
#1050000
1%
#1060000
0%
#1070000
1%
#1080000
0%
#1090000
1%
#1100000
0%
#1110000
1%
#1120000
0%
b10001000100010001000100010001 &
b10001000100010001000100010001 +
b10001000100010001000100010001 8
b10001000100010001000100010001 <
b11000000000000 $
b11000000000000 *
b11000000000000 6
#1130000
b10001000100010001000100010001 2
b10001000100010001000100010001 =
b1 -
b1 ?
b1 1
b1 >
1%
